build/lib/build/lib/build/lib/build/lib/build/lib/build/lib/mocat/__init__.py
build/lib/build/lib/build/lib/build/lib/build/lib/build/lib/mocat/kernels.py
build/lib/build/lib/build/lib/build/lib/build/lib/build/lib/mocat/mcmc.py
build/lib/build/lib/build/lib/build/lib/build/lib/build/lib/mocat/scenarios.py
build/lib/build/lib/build/lib/build/lib/build/lib/build/lib/mocat/smc_samplers.py
build/lib/build/lib/build/lib/build/lib/build/lib/build/lib/mocat/svgd.py
build/lib/build/lib/build/lib/build/lib/build/lib/build/lib/mocat/twodim.py
build/lib/build/lib/build/lib/build/lib/build/lib/build/lib/mocat/utils.py
build/lib/build/lib/build/lib/build/lib/build/lib/build/lib/mocat/version.py
build/lib/build/lib/build/lib/build/lib/build/lib/build/lib/mocat/src/core.py
build/lib/build/lib/build/lib/build/lib/build/lib/build/lib/mocat/src/kernels.py
build/lib/build/lib/build/lib/build/lib/build/lib/build/lib/mocat/src/smc_samplers.py
build/lib/build/lib/build/lib/build/lib/build/lib/build/lib/mocat/src/svgd.py
build/lib/build/lib/build/lib/build/lib/build/lib/build/lib/mocat/src/utils.py
build/lib/build/lib/build/lib/build/lib/build/lib/build/lib/mocat/src/mcmc/corrections.py
build/lib/build/lib/build/lib/build/lib/build/lib/build/lib/mocat/src/mcmc/ensemble_mcmc.py
build/lib/build/lib/build/lib/build/lib/build/lib/build/lib/mocat/src/mcmc/metrics.py
build/lib/build/lib/build/lib/build/lib/build/lib/build/lib/mocat/src/mcmc/run.py
build/lib/build/lib/build/lib/build/lib/build/lib/build/lib/mocat/src/mcmc/sampler.py
build/lib/build/lib/build/lib/build/lib/build/lib/build/lib/mocat/src/mcmc/standard_mcmc.py
build/lib/build/lib/build/lib/build/lib/build/lib/build/lib/mocat/src/scenarios/toy_scenarios.py
build/lib/build/lib/build/lib/build/lib/build/lib/build/lib/mocat/src/scenarios/twodim/toy_scenarios.py
build/lib/build/lib/build/lib/build/lib/build/lib/build/lib/mocat/src/scenarios/twodim/vectorise.py
mocat-0.0.6.dist-info/LICENSE.txt
mocat-0.0.6.dist-info/METADATA
mocat-0.0.6.dist-info/WHEEL
mocat-0.0.6.dist-info/top_level.txt
mocat-0.0.6.dist-info/RECORD
