Metadata-Version: 2.1
Name: mocat
Version: 0.0.6
Summary: Monte Carlo Testbed
Home-page: http://github.com/SamDuffield/mocat
Author: Sam Duffield
Author-email: sddd2@cam.ac.uk
License: MIT
Platform: UNKNOWN
Requires-Python: >=3.6
Requires-Dist: jax
Requires-Dist: jaxlib
Requires-Dist: matplotlib
Requires-Dist: decorator
Requires-Dist: numpy
